<?xml version="1.0" encoding="UTF-8"?>
<workflow id="engine-improvements-workflow" version="1.0">
    <metadata>
        <title>Engine Improvements Implementation Workflow</title>
        <author>Master Workflow 3.0</author>
        <created>2025-11-20T10:00:09.712Z</created>
        <description>Complete implementation workflow for Engine Improvements Implementation Workflow</description>
    </metadata>
    
    <configuration>
        <maxConcurrentTasks>5</maxConcurrentTasks>
        <retryFailedTasks>true</retryFailedTasks>
        <enableMonitoring>true</enableMonitoring>
        <enableValidation>true</enableValidation>
    </configuration>
    
    <phases>
        <phase id="analysis" name="Analysis Phase">
            <tasks>
                <task ref="project-analyzer-implementation" />
            </tasks>
        </phase>
        
        <phase id="engine-implementation" name="Engine Implementation">
            <tasks>
                <task ref="work-stealing-implementation" dependsOn="project-analyzer-implementation" />
                <task ref="circuit-breaker-implementation" dependsOn="work-stealing-implementation" />
                <task ref="advanced-scheduling-implementation" dependsOn="work-stealing-implementation" />
                <task ref="dependency-graph-implementation" dependsOn="circuit-breaker-implementation,advanced-scheduling-implementation" />
                <task ref="monitoring-system-implementation" dependsOn="dependency-graph-implementation" />
            </tasks>
        </phase>
        
        <phase id="autonomous-implementation" name="Autonomous System Implementation">
            <tasks>
                <task ref="documentation-generator-implementation" dependsOn="monitoring-system-implementation" />
                <task ref="specification-engine-implementation" dependsOn="documentation-generator-implementation" />
                <task ref="interactive-installer-implementation" dependsOn="specification-engine-implementation" />
                <task ref="implementation-planner-implementation" dependsOn="interactive-installer-implementation" />
            </tasks>
        </phase>
        
        <phase id="integration" name="Integration & Testing">
            <tasks>
                <task ref="integration-testing" dependsOn="implementation-planner-implementation" />
                <task ref="performance-validation" dependsOn="integration-testing" />
                <task ref="documentation-update" dependsOn="performance-validation" />
            </tasks>
        </phase>
    </phases>
    
    <dependencies>
        <task id="work-stealing-implementation" />
        <task id="circuit-breaker-implementation" />
        <task id="advanced-scheduling-implementation" />
        <task id="dependency-graph-implementation" />
        <task id="monitoring-system-implementation" />
    </dependencies>
    
    <monitoring>
        <trackProgress>true</trackProgress>
        <emitEvents>true</emitEvents>
        <realTimeUpdates>true</realTimeUpdates>
    </monitoring>
</workflow>